[
  {
    "type": "pdf",
    "name": "maib_pdf_transaction",
    "description": "MAIB PDF row with transaction and processing dates, shop description, transaction currency amount, and account MDL amount",
    "pattern": "(?s)^(?P<date>\\d{4}-\\d{2}-\\d{2})\\s+(?P<processing_date>\\d{4}-\\d{2}-\\d{2})\\s+(?P<shop>.+?)(?P<amount>-?(?:\\d{1,3}(?:\\s\\d{3})*|\\d+)\\.\\d{2}[+-]?)\\s+(?P<currency>MDL|RON|USD|EUR)\\s+(?P<amount_mdl>-?(?:\\d{1,3}(?:\\s\\d{3})*|\\d+)\\.\\d{2}[+-]?)(?:\\s+-?(?:\\d{1,3}(?:\\s\\d{3})*|\\d+)\\.\\d{2}[+-]?)?\\b",
    "currency": "auto"
  },
  {
    "type": "pdf",
    "name": "maib_pdf_transaction_single_date",
    "description": "MAIB PDF row with a single transaction date, shop description, transaction currency amount, and optional account MDL amount",
    "pattern": "(?s)^(?!\\d{4}-\\d{2}-\\d{2}\\s+\\d{4}-\\d{2}-\\d{2})(?P<date>\\d{4}-\\d{2}-\\d{2})\\s+(?P<shop>.+?)(?P<amount>-?(?:\\d{1,3}(?:\\s\\d{3})*|\\d+)\\.\\d{2}[+-]?)\\s+(?P<currency>MDL|RON|USD|EUR)(?:\\s+(?P<amount_mdl>-?(?:\\d{1,3}(?:\\s\\d{3})*|\\d+)\\.\\d{2}[+-]?))?(?:\\s+-?(?:\\d{1,3}(?:\\s\\d{3})*|\\d+)\\.\\d{2}[+-]?)?\\b",
    "currency": "auto"
  },
  {
    "type": "pdf",
    "name": "maib_pdf_transaction_dot_date",
    "description": "MAIB PDF row with DD.MM.YYYY dates and MDL amount",
    "pattern": "(?s)(?P<date>\\d{2}\\.\\d{2}\\.\\d{4})\\s+(?:\\d{2}\\.\\d{2}\\.\\d{4})\\s+(?P<shop>.+?)\\s+(?P<amount>-?\\d[\\d\\s.,]*\\.\\d{2}[+-]?)\\s+MDL",
    "currency": "MDL"
  },
  {
    "type": "html",
    "name": "maib_html_transaction",
    "description": "MAIB HTML transaction row with registration date, transaction date, reference, shop, optional currency and amounts",
    "pattern": "(?P<date>\\d{2}-\\d{2}-\\d{4})\\s+(?P<posting_date>\\d{2}-\\d{2}-\\d{4})\\s+(?P<reference>[^\\s]+)\\s+(?P<shop>.+?)\\s+(?:(?P<currency>MDL|USD|EUR)\\s+)?(?:(?P<amount>-?\\d[\\d\\s.,]*\\.\\d{2}[+-]?)\\s+)?(?P<amount_mdl>-?\\d[\\d\\s.,]*\\.\\d{2}[+-]?)$",
    "currency": "auto"
  },
  {
    "type": "html",
    "name": "victoriabank_html_transaction",
    "description": "Victoriabank HTML transaction row with processing date, transaction date, details and MDL amount",
    "pattern": "(?P<processing_date>\\d{2}-\\d{2}-\\d{4})\\s+(?P<transaction_date>\\d{2}-\\d{2}-\\d{4}\\s+\\d{2}:\\d{2}:\\d{2})\\s+(?P<shop>.+?)\\s+(?P<amount>-?\\d[\\d\\s.,]*\\.\\d{2}[+-]?)\\s+MDL",
    "currency": "MDL"
  },
  {
    "type": "html",
    "name": "generic_html_transaction",
    "description": "Fallback generic HTML transaction row with date and MDL amount",
    "pattern": "(?P<date>\\d{2}-\\d{2}-\\d{4})\\s+(?P<shop>.+?)\\s+(?P<amount>-?\\d[\\d\\s.,]*\\.\\d{2}[+-]?)\\s+MDL",
    "currency": "MDL"
  }
]
